lightning_parser_lib/__init__.py
lightning_parser_lib/config_and_parser.py
lightning_parser_lib/number_crunchers/__init__.py
lightning_parser_lib/number_crunchers/database_parser.py
lightning_parser_lib/number_crunchers/lightning_bucketer.py
lightning_parser_lib/number_crunchers/lightning_plotters.py
lightning_parser_lib/number_crunchers/lightning_statistics.py
lightning_parser_lib/number_crunchers/lightning_stitcher.py
lightning_parser_lib/number_crunchers/lightning_visualization.py
lightning_parser_lib/number_crunchers/logger.py
lightning_parser_lib/number_crunchers/toolbox.py
lightning_parser_lib-0.3.50.dist-info/licenses/LICENSE
lightning_parser_lib-0.3.50.dist-info/METADATA
lightning_parser_lib-0.3.50.dist-info/WHEEL
lightning_parser_lib-0.3.50.dist-info/top_level.txt
lightning_parser_lib-0.3.50.dist-info/RECORD
