Metadata-Version: 2.4
Name: lightning_parser_lib
Version: 0.3.50
Summary: Connor's Lightning Parser Lib (LPL) is an extremely powerful analysis utility with a simplistic front-end in mind.
Author-email: Connor White <connor.sw.personal@gmail.com>
License-Expression: MIT
Project-URL: Homepage, https://github.com/CorniiDog/lightning_parser_lib
Project-URL: Issues, https://github.com/CorniiDog/lightning_parser_lib/issues
Classifier: Programming Language :: Python :: 3
Classifier: Operating System :: OS Independent
Requires-Python: >=3.9
License-File: LICENSE
Requires-Dist: pyproj
Requires-Dist: pandas
Requires-Dist: plotly
Requires-Dist: kaleido
Requires-Dist: scipy
Requires-Dist: tqdm
Requires-Dist: numpy
Requires-Dist: imageio
Requires-Dist: process-managerial
Requires-Dist: remote-events
Requires-Dist: datashader
Requires-Dist: matplotlib
Requires-Dist: holoviews
Requires-Dist: geopandas
Requires-Dist: Deprecation
Requires-Dist: lightning-parser-overlays
Dynamic: license-file
